qdds/__init__.py
qdds/cli.py
qdds/version.py
qdds/tests/test_cli.py
qdds-1.2.1.dist-info/licenses/LICENSE
qdds-1.2.1.dist-info/METADATA
qdds-1.2.1.dist-info/WHEEL
qdds-1.2.1.dist-info/entry_points.txt
qdds-1.2.1.dist-info/top_level.txt
qdds-1.2.1.dist-info/RECORD
