Metadata-Version: 2.4
Name: qdds
Version: 1.2.1
Summary: Quick Django Dev Server shortcut using your IP and port 8000
Author-email: Ben McNelly <me@benmcnelly.com>
License: MIT
Requires-Python: >=3.8
License-File: LICENSE
Requires-Dist: click>=8.1
Dynamic: license-file
